__init__.py
solvent_guide/__init__.py
solvent_guide/add_solvent.py
solvent_guide/remove_solvent.py
solvent_guide/reset_solvents.py
solvent_guide/webapp.py
solvent_guide/sources/__init__.py
solvent_guide/sources/blueprints/__init__.py
solvent_guide/sources/blueprints/solvent_guide/CHEM21_full.csv
solvent_guide/sources/blueprints/solvent_guide/__init__.py
solvent_guide/sources/blueprints/solvent_guide/default_colours.txt
solvent_guide/sources/blueprints/solvent_guide/routes.py
solvent_guide/sources/blueprints/solvent_guide/user_colours.txt
solvent_guide/sources/static/css/hazard_colours.css
solvent_guide/sources/static/css/pagestyle.css
solvent_guide/sources/static/js/custom_colours.js
solvent_guide/sources/templates/accessibility.html
solvent_guide/sources/templates/base.html
solvent_guide/sources/templates/solvent_guide.html
solvent_guide/sources/templates/solvent_guide_help.html
solvent_guide-0.4.8.dist-info/LICENSE
solvent_guide-0.4.8.dist-info/METADATA
solvent_guide-0.4.8.dist-info/WHEEL
solvent_guide-0.4.8.dist-info/top_level.txt
solvent_guide-0.4.8.dist-info/RECORD
