Metadata-Version: 2.1
Name: solvent_guide
Version: 0.4.8
Summary: Standalone version of the solvent guide as shown in the AI4Green ELN
Author-email: Joe Heeley <joe.heeley@nottingham.ac.uk>, Samuel Boobier <samuel.boobier@googlemail.com>
Project-URL: Homepage, https://github.com/JoeHeeley2/solvent_flashcards
Project-URL: Bug Tracker, https://github.com/JoeHeeley2/solvent_flashcards/issues
Classifier: Programming Language :: Python :: 3
Classifier: License :: OSI Approved :: GNU Affero General Public License v3
Classifier: Operating System :: OS Independent
Requires-Python: >=3.9
License-File: LICENSE
Requires-Dist: numpy >=1.26.0
Requires-Dist: pandas >=1.4.1
Requires-Dist: blinker >=1.6.2
Requires-Dist: flask >=2.3.2
Requires-Dist: plotly >=5.9.0
Requires-Dist: colorama >=0.4.6
Requires-Dist: python-dateutil >=2.8.2
